whoosh_update/__init__.py
whoosh_update/analysis/__init__.py
whoosh_update/analysis/acore.py
whoosh_update/analysis/analyzers.py
whoosh_update/analysis/filters.py
whoosh_update/analysis/intraword.py
whoosh_update/analysis/morph.py
whoosh_update/analysis/ngrams.py
whoosh_update/analysis/tokenizers.py
whoosh_update/automata/__init__.py
whoosh_update/automata/fsa.py
whoosh_update/automata/glob.py
whoosh_update/automata/lev.py
whoosh_update/automata/nfa.py
whoosh_update/automata/reg.py
whoosh_update/classify.py
whoosh_update/codec/__init__.py
whoosh_update/codec/base.py
whoosh_update/codec/memory.py
whoosh_update/codec/plaintext.py
whoosh_update/codec/whoosh3.py
whoosh_update/collectors.py
whoosh_update/columns.py
whoosh_update/compat.py
whoosh_update/externalsort.py
whoosh_update/fields.py
whoosh_update/filedb/__init__.py
whoosh_update/filedb/compound.py
whoosh_update/filedb/filestore.py
whoosh_update/filedb/filetables.py
whoosh_update/filedb/gae.py
whoosh_update/filedb/structfile.py
whoosh_update/formats.py
whoosh_update/highlight.py
whoosh_update/idsets.py
whoosh_update/index.py
whoosh_update/lang/__init__.py
whoosh_update/lang/dmetaphone.py
whoosh_update/lang/isri.py
whoosh_update/lang/lovins.py
whoosh_update/lang/morph_en.py
whoosh_update/lang/paicehusk.py
whoosh_update/lang/phonetic.py
whoosh_update/lang/porter.py
whoosh_update/lang/porter2.py
whoosh_update/lang/snowball/LICENSE.txt
whoosh_update/lang/snowball/__init__.py
whoosh_update/lang/snowball/bases.py
whoosh_update/lang/snowball/danish.py
whoosh_update/lang/snowball/dutch.py
whoosh_update/lang/snowball/english.py
whoosh_update/lang/snowball/finnish.py
whoosh_update/lang/snowball/french.py
whoosh_update/lang/snowball/german.py
whoosh_update/lang/snowball/hungarian.py
whoosh_update/lang/snowball/italian.py
whoosh_update/lang/snowball/norwegian.py
whoosh_update/lang/snowball/portugese.py
whoosh_update/lang/snowball/romanian.py
whoosh_update/lang/snowball/russian.py
whoosh_update/lang/snowball/spanish.py
whoosh_update-0.1.4.dist-info/LICENSE.txt
whoosh_update-0.1.4.dist-info/METADATA
whoosh_update-0.1.4.dist-info/WHEEL
whoosh_update-0.1.4.dist-info/RECORD
