Metadata-Version: 2.1
Name: whoosh_update
Version: 0.1.4
Summary: Updated version of Whoosh with Python 3.9+ support
Home-page: http://bitbucket.org/mchaput/whoosh
Keywords: index,search,text,spell
Author: Dinga Wonanke
Author-email: bafgreat@gmail.com
Requires-Python: >=3.10,<3.14
Classifier: Programming Language :: Python :: 3
Classifier: Programming Language :: Python :: 3.10
Classifier: Programming Language :: Python :: 3.11
Classifier: Programming Language :: Python :: 3.12
Requires-Dist: cached-property (>=1.5.2,<2.0.0)
Requires-Dist: sphinx (>=8.0,<9.0)
Project-URL: Documentation, http://your-docs-link
Project-URL: Repository, https://github.com/your-repo/whoosh-update
